pycydia
