Metadata-Version: 1.1
Name: pyCydia
Version: 1.0.1
Summary: Cydia API wrapper for Python
Home-page: https://github.com/switchpwn/pyCydia
Author: switchpwn
Author-email: mustiigezen@gmail.com
License: MIT
Download-URL: https://github.com/switchpwn/pyCydia/tarball/1.0
Keywords: cydia api python wrapper
Platform: UNKNOWN
Classifier: License :: OSI Approved :: MIT License
Classifier: Topic :: Software Development :: Libraries :: Python Modules
